structuretoolkit/__init__.py
structuretoolkit/_version.py
structuretoolkit/visualize.py
structuretoolkit/analyse/__init__.py
structuretoolkit/analyse/distance.py
structuretoolkit/analyse/dscribe.py
structuretoolkit/analyse/neighbors.py
structuretoolkit/analyse/phonopy.py
structuretoolkit/analyse/pyscal.py
structuretoolkit/analyse/snap.py
structuretoolkit/analyse/spatial.py
structuretoolkit/analyse/strain.py
structuretoolkit/analyse/symmetry.py
structuretoolkit/build/__init__.py
structuretoolkit/build/aimsgb.py
structuretoolkit/build/compound.py
structuretoolkit/build/mesh.py
structuretoolkit/build/random.py
structuretoolkit/build/sqs.py
structuretoolkit/build/surface.py
structuretoolkit/common/__init__.py
structuretoolkit/common/error.py
structuretoolkit/common/helper.py
structuretoolkit/common/phonopy.py
structuretoolkit/common/pymatgen.py
structuretoolkit/common/pyscal.py
structuretoolkit-0.0.35.dist-info/METADATA
structuretoolkit-0.0.35.dist-info/WHEEL
structuretoolkit-0.0.35.dist-info/licenses/LICENSE
structuretoolkit-0.0.35.dist-info/RECORD
