Metadata-Version: 2.4
Name: structuretoolkit
Version: 0.0.35
Summary: build, analyse and visualise atomistic structures for materials science
Project-URL: Homepage, https://github.com/pyiron/structuretoolkit
Project-URL: Documentation, https://github.com/pyiron/structuretoolkit
Project-URL: Repository, https://github.com/pyiron/structuretoolkit
Author-email: Jan Janssen <janssen@mpie.de>
License: BSD 3-Clause License
License-File: LICENSE
Keywords: pyiron
Classifier: Development Status :: 5 - Production/Stable
Classifier: Intended Audience :: Science/Research
Classifier: License :: OSI Approved :: BSD License
Classifier: Operating System :: OS Independent
Classifier: Programming Language :: Python :: 3.9
Classifier: Programming Language :: Python :: 3.10
Classifier: Programming Language :: Python :: 3.11
Classifier: Programming Language :: Python :: 3.12
Classifier: Topic :: Scientific/Engineering :: Physics
Requires-Python: <3.13,>=3.9
Requires-Dist: ase<=3.26.0,>=3.20.1
Requires-Dist: numpy<=2.3.3,>=1.23.5
Requires-Dist: scipy<=1.16.2,>=1.9.3
Provides-Extra: clusters
Requires-Dist: scikit-learn==1.6.1; extra == 'clusters'
Provides-Extra: dscribe
Requires-Dist: dscribe==2.1.2; extra == 'dscribe'
Provides-Extra: grainboundary
Requires-Dist: aimsgb<=1.1.1,>=1.0.2; extra == 'grainboundary'
Requires-Dist: pymatgen<=2025.3.10,>=2022.2.1; extra == 'grainboundary'
Provides-Extra: matplotlib
Requires-Dist: matplotlib==3.10.3; extra == 'matplotlib'
Provides-Extra: nglview
Requires-Dist: nglview<=3.1.4,>=2.7.7; extra == 'nglview'
Provides-Extra: phonopy
Requires-Dist: phonopy<=2.43.2,>=2.16.2; extra == 'phonopy'
Requires-Dist: spglib<=2.6.0,>=1.16.5; extra == 'phonopy'
Provides-Extra: plotly
Requires-Dist: plotly<=6.3.0,>=4.14.3; extra == 'plotly'
Provides-Extra: pyscal
Requires-Dist: pyscal3<=3.3.0,>=3.2.5; extra == 'pyscal'
Provides-Extra: pyxtal
Requires-Dist: pyxtal<=1.1.1,>=0.5.5; extra == 'pyxtal'
Provides-Extra: surface
Requires-Dist: pymatgen<=2025.3.10,>=2022.2.1; extra == 'surface'
Requires-Dist: spglib<=2.6.0,>=1.16.5; extra == 'surface'
Provides-Extra: symmetry
Requires-Dist: spglib<=2.6.0,>=1.16.5; extra == 'symmetry'
